main.py
zpace-0.2.0.dist-info/METADATA
zpace-0.2.0.dist-info/WHEEL
zpace-0.2.0.dist-info/entry_points.txt
zpace-0.2.0.dist-info/RECORD
