Metadata-Version: 2.4
Name: zpace
Version: 0.2.0
Summary: A CLI tool to discover what's consuming your disk space
Author-email: Ąžuolas Krušna <azuolas.krusna@yahoo.com>
License: Apache-2.0
Keywords: analyze,cleanup,cli,disk,file,space,storage
Classifier: Development Status :: 4 - Beta
Classifier: Environment :: Console
Classifier: Intended Audience :: Developers
Classifier: Intended Audience :: System Administrators
Classifier: License :: OSI Approved :: Apache Software License
Classifier: Operating System :: MacOS
Classifier: Programming Language :: Python :: 3
Classifier: Programming Language :: Python :: 3.9
Classifier: Programming Language :: Python :: 3.10
Classifier: Programming Language :: Python :: 3.11
Classifier: Programming Language :: Python :: 3.12
Classifier: Programming Language :: Python :: 3.13
Classifier: Programming Language :: Python :: 3.14
Classifier: Topic :: System :: Filesystems
Classifier: Topic :: Utilities
Requires-Python: >=3.9
Requires-Dist: argparse>=1.4.0
Requires-Dist: tqdm>=4.67.1
